factoirc/__init__.py
factoirc/irc_colors.py
factoirc/log_parser.py
factoirc/rcon.py
factoirc/readers.py
factoirc/utils.py
factoirc-0.6.dist-info/DESCRIPTION.rst
factoirc-0.6.dist-info/METADATA
factoirc-0.6.dist-info/RECORD
factoirc-0.6.dist-info/WHEEL
factoirc-0.6.dist-info/metadata.json
factoirc-0.6.dist-info/top_level.txt
