Metadata-Version: 2.0
Name: factoirc
Version: 0.6
Summary: Bidirectional IRC bridge for Factorio
Home-page: https://github.com/mickael9/factoirc
Author: Mickaël Thomas
Author-email: mickael9@gmail.com
License: MIT
Keywords: factorio irc
Platform: UNKNOWN
Classifier: Development Status :: 3 - Alpha
Classifier: Operating System :: OS Independent
Classifier: License :: OSI Approved :: MIT License
Classifier: Programming Language :: Python :: 3 :: Only
Classifier: Programming Language :: Python :: 3.5
Classifier: Topic :: Communications :: Chat :: Internet Relay Chat
Classifier: Topic :: Games/Entertainment
Requires-Dist: irc3
Provides-Extra: systemd
Requires-Dist: python-systemd; extra == 'systemd'
